setup.py
mimimongo.egg-info/PKG-INFO
mimimongo.egg-info/SOURCES.txt
mimimongo.egg-info/dependency_links.txt
mimimongo.egg-info/not-zip-safe
mimimongo.egg-info/requires.txt
mimimongo.egg-info/top_level.txt
minimongo/__init__.py
minimongo/collection.py
minimongo/config.py
minimongo/exceptions.py
minimongo/index.py
minimongo/model.py
minimongo/options.py
minimongo/tests/__init__.py
minimongo/tests/test_model.py
minimongo/tests/test_utils.py