Metadata-Version: 1.0
Name: mimimongo
Version: 0.1.2
Summary: Minimal database Model management for MongoDB
Home-page: http://github.com/yablokoff/minimongo
Author: Steve Lacy, Dmitrii Vlasov
Author-email: yablokoff.tlt@gmail.com
License: UNKNOWN
Keywords: mongo,mongodb,pymongo,orm
Platform: any
Classifier: Development Status :: 3 - Alpha
Classifier: Intended Audience :: Developers
Classifier: Programming Language :: Python
Classifier: Topic :: Database
